asyncpg_utils/__init__.py
asyncpg_utils/databases.py
asyncpg_utils/managers.py
asyncpg_utils/templates.py
asyncpg_utils-0.6.0.dist-info/DESCRIPTION.rst
asyncpg_utils-0.6.0.dist-info/METADATA
asyncpg_utils-0.6.0.dist-info/RECORD
asyncpg_utils-0.6.0.dist-info/WHEEL
asyncpg_utils-0.6.0.dist-info/metadata.json
asyncpg_utils-0.6.0.dist-info/top_level.txt
