Metadata-Version: 2.0
Name: asyncpg-utils
Version: 0.6.0
Summary: Utilities for Asyncpg
Home-page: https://github.com/allisson/asyncpg-utils
Author: Allisson Azevedo
Author-email: allisson@gmail.com
License: UNKNOWN
Platform: UNKNOWN
Classifier: Development Status :: 3 - Alpha
Classifier: Intended Audience :: Developers
Classifier: Programming Language :: Python :: 3.5
Classifier: Programming Language :: Python :: 3.6
Classifier: Topic :: Software Development :: Libraries
Requires-Dist: asyncpg (>=0.14.0)
Requires-Dist: Jinja2 (>=2.10)
